genocide/brokers.py
genocide/clients.py
genocide/command.py
genocide/configs.py
genocide/defines.py
genocide/handler.py
genocide/loggers.py
genocide/message.py
genocide/methods.py
genocide/objects.py
genocide/persist.py
genocide/repeats.py
genocide/serials.py
genocide/statics.py
genocide/threads.py
genocide/timings.py
genocide/utility.py
genocide/workdir.py
genocide/modules/__init__.py
genocide/modules/atr.py
genocide/modules/flt.py
genocide/modules/fnd.py
genocide/modules/irc.py
genocide/modules/log.py
genocide/modules/lst.py
genocide/modules/man.py
genocide/modules/mbx.py
genocide/modules/mdl.py
genocide/modules/pth.py
genocide/modules/req.py
genocide/modules/rss.py
genocide/modules/rst.py
genocide/modules/sil.py
genocide/modules/slg.py
genocide/modules/tdo.py
genocide/modules/thr.py
genocide/modules/tmr.py
genocide/modules/udp.py
genocide/modules/upt.py
genocide/modules/web.py
genocide/modules/wsd.py
genocide/network/__init__.py
genocide/nucleus/about.html
genocide/nucleus/evidence.html
genocide/nucleus/genindex-all.html
genocide/nucleus/genindex.html
genocide/nucleus/guilty.html
genocide/nucleus/index.html
genocide/nucleus/manual.html
genocide/nucleus/objects.inv
genocide/nucleus/pubchem.html
genocide/nucleus/reconsider.html
genocide/nucleus/request.html
genocide/nucleus/robots.txt
genocide/nucleus/search.html
genocide/nucleus/searchindex.js
genocide/nucleus/writings.html
genocide/nucleus/_images/ECHAabilify.png
genocide/nucleus/_images/ECHAclozapine.png
genocide/nucleus/_images/ECHAhaldol.png
genocide/nucleus/_images/ECHAzyprexa.png
genocide/nucleus/_images/OTP111.png
genocide/nucleus/_images/OTP222.png
genocide/nucleus/_images/abilifypubchem.png
genocide/nucleus/_images/ack3.png
genocide/nucleus/_images/bevestigd.jpg
genocide/nucleus/_images/clozapinepubchem.png
genocide/nucleus/_images/genocide.png
genocide/nucleus/_images/haldolpubchem.png
genocide/nucleus/_images/informed.jpg
genocide/nucleus/_images/kamer2.png
genocide/nucleus/_images/skull3.png
genocide-230.dist-info/METADATA
genocide-230.dist-info/WHEEL
genocide-230.dist-info/top_level.txt
genocide-230.dist-info/RECORD
