Metadata-Version: 2.4
Name: genocide
Version: 230
Summary: Since 4 march 2019
Author-email: Bart Thate <bthate@dds.nl>
License-Expression: Unlicense
Project-URL: home, https://pypi.org/project/genocide
Project-URL: bugs, https://github.com/bthate/genocide/issues
Project-URL: source, https://github.com/bthate/genocide
Classifier: Development Status :: 3 - Alpha
Classifier: Operating System :: Unix
Classifier: Programming Language :: Python
Classifier: Topic :: Utilities
